hostess/__init__.py
hostess/argscratch.py
hostess/caller.py
hostess/directory.py
hostess/monitors.py
hostess/profilers.py
hostess/serverpool.py
hostess/shortcuts.py
hostess/ssh.py
hostess/subutils.py
hostess/tdscratch.py
hostess/utilities.py
hostess/aws/__init__.py
hostess/aws/ec2.py
hostess/aws/ecs.py
hostess/aws/pricing.py
hostess/aws/s3.py
hostess/aws/utilities.py
hostess/aws/s3transfer_extensions/__init__.py
hostess/aws/s3transfer_extensions/processpool_range.py
hostess/aws/s3transfer_extensions/threadpool_range.py
hostess/aws/tests/__init__.py
hostess/aws/tests/aws_test_utils.py
hostess/aws/tests/test_ec2.py
hostess/aws/tests/test_s3.py
hostess/config/__init__.py
hostess/config/config.py
hostess/config/user_config.py
hostess/station/__init__.py
hostess/station/actors.py
hostess/station/bases.py
hostess/station/comm.py
hostess/station/delegates.py
hostess/station/handlers.py
hostess/station/launchallscratch.py
hostess/station/messages.py
hostess/station/proto_utils.py
hostess/station/shutscratch.py
hostess/station/station.py
hostess/station/talkie.py
hostess/station/proto/__init__.py
hostess/station/proto/station.proto
hostess/station/proto/station_pb2.py
hostess/station/situation/__init__.py
hostess/station/situation/_textual_monkeypatch.py
hostess/station/situation/app.py
hostess/station/situation/interface_organizers.py
hostess/station/situation/loopquery.py
hostess/station/situation/response_organizers.py
hostess/station/situation/sitstation.py
hostess/station/situation/widgets.py
hostess/station/tests/__init__.py
hostess/station/tests/target_functions.py
hostess/station/tests/test_handler.py
hostess/station/tests/test_station.py
hostess/station/tests/test_talkie.py
hostess/station/tests/testing_actors.py
hostess/station/tests/test_data/squirrel.jpg
hostess/tests/__init__.py
hostess/tests/test_caller.py
hostess/tests/test_directory.py
hostess/tests/test_monitors.py
hostess/tests/test_profilers.py
hostess/tests/test_subutils.py
hostess-0.11.4.dist-info/licenses/LICENSE
hostess-0.11.4.dist-info/METADATA
hostess-0.11.4.dist-info/WHEEL
hostess-0.11.4.dist-info/top_level.txt
hostess-0.11.4.dist-info/RECORD
