Metadata-Version: 2.4
Name: hostess
Version: 0.11.4
Summary: intuitive admin library
Author-email: "M. St. Clair" <mstclair@millionconcepts.com>, Sierra Brown <sierra@millionconcepts.com>, Chase Million <chase@millionconcepts.com>
License-Expression: BSD-3-Clause
Project-URL: Repository, https://github.com/MillionConcepts/hostess
Project-URL: Documentation, https://hostess.readthedocs.io/en/latest/
Project-URL: Changelog, https://hostess.readthedocs.io/en/latest/version_history/
Classifier: Development Status :: 4 - Beta
Classifier: Environment :: Console
Classifier: Intended Audience :: Developers
Classifier: Operating System :: MacOS :: MacOS X
Classifier: Operating System :: POSIX :: Linux
Classifier: Programming Language :: Python :: 3
Classifier: Programming Language :: Unix Shell
Requires-Python: >=3.10
License-File: LICENSE
Requires-Dist: cytoolz
Requires-Dist: dustgoggles
Requires-Dist: invoke
Requires-Dist: more-itertools
Requires-Dist: pandas
Requires-Dist: psutil
Requires-Dist: pyyaml
Requires-Dist: requests
Requires-Dist: rich
Provides-Extra: aws
Requires-Dist: boto3; extra == "aws"
Requires-Dist: fabric; extra == "aws"
Provides-Extra: directory
Requires-Dist: python-magic; extra == "directory"
Provides-Extra: profilers
Requires-Dist: pympler; extra == "profilers"
Provides-Extra: ssh
Requires-Dist: fabric; extra == "ssh"
Provides-Extra: station
Requires-Dist: dill; extra == "station"
Requires-Dist: fire; extra == "station"
Requires-Dist: protobuf; extra == "station"
Requires-Dist: textual; extra == "station"
Provides-Extra: tests
Requires-Dist: pillow; extra == "tests"
Requires-Dist: pytest; extra == "tests"
Dynamic: license-file
